<ArGpsLocationData><Entry><id>0</id><lat>37.55822034776672</lat><lng>127.000167256466</lng><altitude>0</altitude><altitudeMode>GroundRelative</altitudeMode><name>Dongguk1</name><meshId>Logo</meshId><movementSmoothing>0.05</movementSmoothing><maxNumberOfLocationUpdates>0</maxNumberOfLocationUpdates><useMovingAverage>false</useMovingAverage><hideObjectUtilItIsPlaced>true</hideObjectUtilItIsPlaced></Entry><Entry><id>1</id><lat>37.55782035197467</lat><lng>126.99999688015754</lng><altitude>0</altitude><altitudeMode>GroundRelative</altitudeMode><name>Dongguk2</name><meshId>Logo</meshId><movementSmoothing>0.05</movementSmoothing><maxNumberOfLocationUpdates>0</maxNumberOfLocationUpdates><useMovingAverage>false</useMovingAverage><hideObjectUtilItIsPlaced>true</hideObjectUtilItIsPlaced></Entry><Entry><id>2</id><lat>37.55927179521689</lat><lng>126.99444227927597</lng><altitude>0</altitude><altitudeMode>GroundRelative</altitudeMode><name>Namsnagol</name><meshId>Logo</meshId><movementSmoothing>0.05</movementSmoothing><maxNumberOfLocationUpdates>0</maxNumberOfLocationUpdates><useMovingAverage>false</useMovingAverage><hideObjectUtilItIsPlaced>true</hideObjectUtilItIsPlaced></Entry><Entry><id>3</id><lat>37.57805129702214</lat><lng>126.97698024127516</lng><altitude>0</altitude><altitudeMode>GroundRelative</altitudeMode><name>Gyeongbokgung</name><meshId>Logo</meshId><movementSmoothing>0.05</movementSmoothing><maxNumberOfLocationUpdates>0</maxNumberOfLocationUpdates><useMovingAverage>false</useMovingAverage><hideObjectUtilItIsPlaced>true</hideObjectUtilItIsPlaced></Entry><Entry><id>4</id><lat>37.5713564493428</lat><lng>126.99500149658832</lng><altitude>0</altitude><altitudeMode>GroundRelative</altitudeMode><name>Jongmyo</name><meshId>Logo</meshId><movementSmoothing>0.05</movementSmoothing><maxNumberOfLocationUpdates>0</maxNumberOfLocationUpdates><useMovingAverage>false</useMovingAverage><hideObjectUtilItIsPlaced>true</hideObjectUtilItIsPlaced></Entry><Entry><id>5</id><lat>37.541986197625334</lat><lng>127.03916386340467</lng><altitude>0</altitude><altitudeMode>GroundRelative</altitudeMode><name>Seoulforest</name><meshId>Logo</meshId><movementSmoothing>0.05</movementSmoothing><maxNumberOfLocationUpdates>0</maxNumberOfLocationUpdates><useMovingAverage>false</useMovingAverage><hideObjectUtilItIsPlaced>true</hideObjectUtilItIsPlaced></Entry><Entry><id>6</id><lat>37.5235329155187</lat><lng>126.98108122027202</lng><altitude>0</altitude><altitudeMode>GroundRelative</altitudeMode><name>NationalMuseum</name><meshId>Logo</meshId><movementSmoothing>0.05</movementSmoothing><maxNumberOfLocationUpdates>0</maxNumberOfLocationUpdates><useMovingAverage>false</useMovingAverage><hideObjectUtilItIsPlaced>true</hideObjectUtilItIsPlaced></Entry><Entry><id>7</id><lat>37.54534234560987</lat><lng>126.96057261109121</lng><altitude>0</altitude><altitudeMode>GroundRelative</altitudeMode><name>Hyochang</name><meshId>Logo</meshId><movementSmoothing>0.05</movementSmoothing><maxNumberOfLocationUpdates>0</maxNumberOfLocationUpdates><useMovingAverage>false</useMovingAverage><hideObjectUtilItIsPlaced>true</hideObjectUtilItIsPlaced></Entry><Entry><id>8</id><lat>37.55118124860192</lat><lng>126.98829556293555</lng><altitude>0</altitude><altitudeMode>GroundRelative</altitudeMode><name>NamsanPark</name><meshId>Logo</meshId><movementSmoothing>0.05</movementSmoothing><maxNumberOfLocationUpdates>0</maxNumberOfLocationUpdates><useMovingAverage>false</useMovingAverage><hideObjectUtilItIsPlaced>true</hideObjectUtilItIsPlaced></Entry><Entry><id>9</id><lat>37.554861917352284</lat><lng>126.97840844325736</lng><altitude>0</altitude><altitudeMode>GroundRelative</altitudeMode><name>WallofSeoul</name><meshId>Logo</meshId><movementSmoothing>0.05</movementSmoothing><maxNumberOfLocationUpdates>0</maxNumberOfLocationUpdates><useMovingAverage>false</useMovingAverage><hideObjectUtilItIsPlaced>true</hideObjectUtilItIsPlaced></Entry><Entry><id>10</id><lat>37.57088097853273</lat><lng>126.96811542553195</lng><altitude>0</altitude><altitudeMode>GroundRelative</altitudeMode><name>Gyeonghuigung</name><meshId>Logo</meshId><movementSmoothing>0.05</movementSmoothing><maxNumberOfLocationUpdates>0</maxNumberOfLocationUpdates><useMovingAverage>false</useMovingAverage><hideObjectUtilItIsPlaced>true</hideObjectUtilItIsPlaced></Entry><Entry><id>11</id><lat>37.567539675331844</lat><lng>126.8863924430313</lng><altitude>0</altitude><altitudeMode>GroundRelative</altitudeMode><name>HaneulPark</name><meshId>Logo</meshId><movementSmoothing>0.05</movementSmoothing><maxNumberOfLocationUpdates>0</maxNumberOfLocationUpdates><useMovingAverage>false</useMovingAverage><hideObjectUtilItIsPlaced>true</hideObjectUtilItIsPlaced></Entry></ArGpsLocationData>